<?xml version="1.0" encoding="utf-8"?>
<skel>
    <forms>
        <form id="channel_details" title="Show all items from remote channel" />
        <form id="delete_confirmation" title="Delete confirmation"/>
        <form id="folder_add" title="NyFolder add"/>
        <form id="folder_administration_basket" title="Folder administration - centralized basket form"/>
        <form id="folder_administration_feedback" title="Folder administration - customize feedback form"/>
        <form id="folder_administration_logo" title="Folder administration - change logo"/>
        <form id="folder_administration_portlets" title="Folder administration - right side portlets"/>
        <form id="folder_administration_source" title="Folder administration - acl_users source"/>
        <form id="folder_administration_users" title="Folder administration - users' management"/>
        <form id="folder_basketofapprovals" title="NyFolder basket of approvals"/>
        <form id="folder_basketofvalidation" title="NyFolder basket of invalid items"/>
        <form id="folder_edit" title="NyFolder edit"/>
        <form id="folder_editlogo" title="NyFolder edit logo"/>
        <form id="folder_index" title="NyFolder default view"/>
        <form id="folder_listing" title="NyFolder contents"/>
        <form id="folder_menusubmissions" title="NyFolder menu of submissions"/>
        <form id="folder_renameid" title="NyFolder rename subitems ids"/>
        <form id="folder_restrict" title="NyFolder restrictions"/>
        <form id="folder_sortorder" title="NyFolder sort order"/>
        <form id="folder_subobjects" title="NyFolder subobjects"/>
        <form id="form_languages_box" title="Box for changing the language when translating content"/>
        <form id="languages_box" title="Box for changing the language on pages"/>
        <form id="messages_box" title="Box for info or error messages"/>
        <form id="site_admin_adduser" title="Portal administration - add user"/>
        <form id="site_admin_importusers" title="Portal administration - import users"/>
        <form id="site_admin_all_users" title="Portal administration - all users"/>
        <form id="site_admin_assignroles" title="Portal administration - assign roles"/>
        <form id="site_admin_basket" title="Portal administration - centralized basket form"/>
        <form id="site_admin_centre" title="Portal administration - centre"/>
        <form id="site_admin_documentation" title="Portal administration - documentation"/>
        <form id="site_admin_editor" title="Portal administration - editor settings"/>
        <form id="site_admin_edituser" title="Portal administration - edit user"/>
        <form id="site_admin_editrole" title="Portal administration - edit role"/>
        <form id="site_admin_email" title="Portal administration - email settings"/>
        <form id="site_admin_folderportlets" title="Portal administration - portlets for folders section"/>
        <form id="site_admin_frontportlets" title="Portal administration - front portlets section"/>
        <form id="site_admin_htmlportlets" title="Portal administration - html portlets section"/>
        <form id="site_admin_layout" title="Portal administration - layout"/>
        <form id="site_admin_leftportlets" title="Portal administration - left portlets section"/>
        <form id="site_admin_linkslist" title="Portal administration - list of links"/>
        <form id="site_admin_linkslists" title="Portal administration - lists of links"/>
        <form id="site_admin_linksportlets" title="Portal administration - list of links portlets section"/>
        <form id="site_admin_localchannels" title="Portal administration - local channels"/>
        <form id="site_admin_localchportlets" title="Portal administration - local channels section"/>
        <form id="site_admin_local_users" title="Portal administration - local users"/>
        <form id="site_admin_logos" title="Portal administration - logos"/>
        <form id="site_admin_maintopics" title="Portal administration - main sections"/>
        <form id="site_admin_metadata" title="Portal administration - medata"/>
        <form id="site_admin_network" title="Portal administration - network portals"/>
        <form id="site_admin_properties" title="Portal administration - properties"/>
        <form id="site_admin_reflist" title="Portal administration - list of items"/>
        <form id="site_admin_reflists" title="Portal administration - selection lists"/>
        <form id="site_admin_remotechannels" title="Portal administration - remote channels"/>
        <form id="site_admin_remotechannels_aggregators" title="Portal administration - remote channels aggregators"/>
        <form id="site_admin_remotechportlets" title="Portal administration - remote channels portlets section"/>
        <form id="site_admin_rightportlets" title="Portal administration - right portlets section"/>
        <form id="site_admin_roles" title="Portal administration - users and roles"/>
        <form id="site_admin_sources" title="Portal administration - other users sources"/>
        <form id="site_admin_specialportlets" title="Portal administration - system portlets section"/>
        <form id="site_admin_template" title="Portal administration - macro"/>
        <form id="site_admin_users" title="Portal administration - users"/>
        <form id="site_admin_validation" title="Portal administration - content checking and validation"/>
        <form id="site_admin_validation_tree" title="Portal administration - reports of content checking and validation"/>
        <form id="site_admin_versioncontrol" title="Portal administration - version control"/>
        <form id="site_admin_folder_subobjects" title="Portal administration - Folder subobjects"/>
        <form id="site_changecredentials" title="Portal change user credentials"/>
        <form id="site_external_search" title="Portal external search"/>
        <form id="site_feedback" title="Portal feedback"/>
        <form id="site_googleanalytics" title="Google Analytics script"/>
        <form id="site_index" title="Portal home page"/>
        <form id="site_login" title="Portal login"/>
        <form id="site_logout" title="Portal logout"/>
        <form id="site_macro_add" title="Macro for add forms"/>
        <form id="site_macro_edit" title="Macro for edit forms"/>
        <form id="site_macro_schema_add" title="Macro for add forms using schemas"/>
        <form id="site_macro_schema_edit" title="Macro for edit forms using schemas"/>
        <form id="site_menusubmissions" title="Site menu for submissions"/>
        <form id="site_messages" title="Portal messages page"/>
        <form id="site_object_index" title="Macros to render bits of object index pages"/>
        <form id="site_requestrole" title="Portal request role"/>
        <form id="site_scripts" title="Portal site global scripts"/>
        <form id="site_search" title="Portal search"/>
        <form id="site_sitemap" title="Portal site map"/>
        <form id="site_styles" title="Portal site global styles"/>
        <form id="site_unauthorized" title="Portal logout"/>
        <form id="site_userprofile" title="Default user profile sheet"/>
        <form id="sitemap_add" title="Sitemap for picklists"/>
        <form id="sitemap_xml" title="Google sitemap"/>
        <form id="standard_error_message" title="Portal standard error page"/>
    </forms>
    <layout default_skin_id="skin" default_scheme_id="scheme">
        <skin id="skin" title="Flowerpower">
            <file id="common.css" title=""/>
            <template id="element_breadcrumb" title="element breadcrumb"/>
            <template id="element_footer" title="element footer"/>
            <template id="element_disclaimer" title="element disclaimer"/>
            <template id="element_header" title="element header"/>
            <template id="folder_administration_macro" title="Folder administration macro page"/>
            <file id="ie7.css" title=""/>
            <file id="ie8.css" title=""/>
            <file id="ie9.css" title=""/>
            <template id="portlet_center_macro" title="Macro for center portlets"/>
            <template id="portlet_left_macro" title="Macro for left portlets"/>
            <template id="portlet_right_macro" title="Macro for right portlets"/>
            <template id="site_index" title="Portal homepage index"/>
            <template id="standard_template" title="Portal standard template"/>
            <scheme id="scheme" title="Color blue">
                <file id="style.css" title=""/>
                <image id="background_left_portlet.png" title=""/>
                <image id="background_right_portlet.png" title=""/>
                <image id="bg-lang-btns.gif" title=""/>
                <image id="powered.gif" title="Powered"/>
                <image id="screenshot.gif" title="Skin screenshot"/>
                <image id="addcomment.gif" title="Add comment"/>
                <image id="comment.gif" title="Comment icon"/>
                <image id="logintoadd.gif" title="Login to add"/>
                <image id="trash.gif" title="Trash"/>
                <image id="sort_asc.gif" title="Sort in ascending order"/>
                <image id="sort_desc.gif" title="Sort in descending order"/>
                <image id="sort_not.gif" title="Not sortable"/>
                <image id="translate.gif" title="Translating language"/>
                <image id="header-bg.gif" title="Header background"/>
                <image id="left-li-bg.gif" title="Left background"/>
                <image id="menunav-a-hover.gif" title="Menu hover"/>
                <image id="menunav-bg.gif" title="Menunav background"/>
                <image id="ep_collapse.gif" title="Collapse icon for expandable portlets"/>
                <image id="ep_expand.gif" title="Expand icon for expandable portlets"/>
                <image id="ep_none.gif" title="Blank icon for expandable portlets"/>
            </scheme>
        </skin>
    </layout>
    <pluggablecontenttypes>
        <pluggablecontenttype meta_type="Naaya News" action="1"/>
        <pluggablecontenttype meta_type="Naaya Event" action="1"/>
        <pluggablecontenttype meta_type="Naaya Document" action="1"/>
        <pluggablecontenttype meta_type="Naaya URL" action="1"/>
        <pluggablecontenttype meta_type="Naaya File" action="1"/>
        <pluggablecontenttype meta_type="Naaya Pointer" action="1"/>
        <pluggablecontenttype meta_type="Naaya Story" action="1"/>
    </pluggablecontenttypes>
    <syndication>
        <namespace id="101" prefix="rdf" value="http://www.w3.org/1999/02/22-rdf-syntax-ns#"/>
        <namespace id="102" prefix="dc" value="http://purl.org/dc/elements/1.1/"/>
        <namespace id="103" prefix="ev" value="http://purl.org/rss/1.0/modules/event/"/>
        <namespace id="104" prefix="" value="http://purl.org/rss/1.0/"/>
        <channeltype id="News" title="News"/>
        <channeltype id="Events" title="Events"/>
        <channeltype id="Stories" title="Stories"/>
        <scriptchannel id="latestuploads_rdf" title="Latest uploads" description="Latest uploads" language="en" type="Miscellaneous" numberofitems="5" portlet="1"/>
        <scriptchannel id="latestcomments_rdf" title="Latest comments" description="Latest comments" language="en" type="Miscellaneous" numberofitems="5" portlet="1"/>
        <scriptchannel id="latestnews_rdf" title="Latest news" description="Latest news" language="en" type="News" numberofitems="5" portlet="1"/>
        <scriptchannel id="lateststories_rdf" title="Selected stories" description="Selected stories" language="en" type="Stories" numberofitems="5" portlet="1"/>
        <scriptchannel id="upcomingevents_rdf" title="Upcoming events" description="Upcoming events" language="en" type="Events" numberofitems="5" portlet="1"/>
        <scriptchannel id="pastevents_rdf" title="Past events" description="Past events" language="en" type="Events" numberofitems="5" portlet="1"/>
        <scriptchannel id="latestevents_rdf" title="Latest events" description="Latest events" language="en" type="Events" numberofitems="5" portlet="0"/>
        <!-- remotechannel id="" title="Example" url="http://" numbershownitems="10" /-->
    </syndication>
    <portlets left="portlet_maincategories" center="portlet_lateststories_rdf,portlet_latestnews_rdf,portlet_upcomingevents_rdf,portlet_latestuploads_rdf">
        <portlet id="portlet_localchannels" title="Local channels" />
        <portlet id="portlet_folder_administration" title="Folder Administration" />
        <linkslist id="topnav_links" title="Top navigation links" portlet="">
            <link id="102" title="EauDeWeb" description="Eaudeweb Romania" url="http://www.eaudeweb.ro" relative="0" permission="" order="2"/>
            <link id="103" title="Naaya" description="Naaya" url="http://naaya.eaudeweb.ro/" relative="0" permission="" order="3"/>
        </linkslist>
        <linkslist id="menunav_links" title="Menu navigation links" portlet="">
            <link id="102" title="Login" description="Login page" url="login_html" relative="0" permission="" order="2"/>
            <link id="109" title="Sitemap" description="" url="/sitemap_html" relative="1" permission="" order="9"/>
            <link id="110" title="Administration" description="" url="/admin_centre_html" relative="1" permission="" order="10"/>
        </linkslist>
        <reflist id="event_types" title="Event types" description="Types of events used by Naaya Event objects. When adding or editing events, the end users will be able to choose from list below.">
            <item id="meeting" title="Meeting"/>
            <item id="event" title="Event"/>
            <item id="conference" title="Conference"/>
            <item id="other" title="Other"/>
        </reflist>
    </portlets>
    <properties>
        <language code="en" />
    </properties>
    <emails>
        <emailtemplate id="email_feedback" title="Feedback"/>
        <emailtemplate id="email_notifyonerrors" title="Notification on errors"/>
        <emailtemplate id="email_requestrole" title="Request role"/>
        <emailtemplate id="email_createaccount" title="Create account notification"/>
        <emailtemplate id="email_confirmuser" title="New user registration confirmation"/>
    </emails>
    <security>
        <role name="Administrator">
            <permission name="Access Transient Objects" />
            <permission name="Access contents information" />
            <permission name="Access session data" />
            <permission name="Add Naaya Forum" />
            <permission name="Add Naaya Forum Message" />
            <permission name="Add/Edit/Delete Naaya Forum Topic" />
            <permission name="Change permissions" />
            <permission name="Edit/Delete Forum Message" />
            <permission name="Manage Naaya Glossary" />
            <permission name="Manage users" />
            <permission name="Naaya - Access administrative area" />
            <permission name="Naaya - Add comments for content" />
            <permission name="Naaya - Add Naaya Blob File objects" />
            <permission name="Naaya - Add Naaya Contact objects" />
            <permission name="Naaya - Add Naaya Document objects" />
            <permission name="Naaya - Add Naaya Event objects" />
            <permission name="Naaya - Add Naaya Folder objects" />
            <permission name="Naaya - Add Naaya GeoPoint objects" />
            <permission name="Naaya - Add Naaya Media File objects" />
            <permission name="Naaya - Add Naaya Meeting objects" />
            <permission name="Naaya - Add Naaya Mega Survey" />
            <permission name="Naaya - Add Naaya News objects" />
            <permission name="Naaya - Add Naaya Photo" />
            <permission name="Naaya - Add Naaya Photo Folder" />
            <permission name="Naaya - Add Naaya Photo Gallery" />
            <permission name="Naaya - Add Naaya Pointer objects" />
            <permission name="Naaya - Add Naaya Story objects" />
            <permission name="Naaya - Add Naaya Survey Answer" />
            <permission name="Naaya - Add Naaya Survey Attachment" />
            <permission name="Naaya - Add Naaya Survey Report" />
            <permission name="Naaya - Add Naaya TalkBack Consultation objects" />
            <permission name="Naaya - Add Naaya URL objects" />
            <permission name="Naaya - Add Naaya Youtube objects" />
            <permission name="Naaya - Copy content" />
            <permission name="Naaya - Create user" />
            <permission name="Naaya - Delete content" />
            <permission name="Naaya - Edit Naaya Survey Answers" />
            <permission name="Naaya - Edit content" />
            <permission name="Naaya - Invite to TalkBack Consultation" />
            <permission name="Naaya - Manage TalkBack Consultation" />
            <permission name="Naaya - Manage comments for content" />
            <permission name="Naaya - Meeting - Administrate the meeting" />
            <permission name="Naaya - Meeting - Participate in the meeting" />
            <permission name="Naaya - Publish content" />
            <permission name="Naaya - Publish direct" />
            <permission name="Naaya - Request Webex" />
            <permission name="Naaya - Review TalkBack Consultation" />
            <permission name="Naaya - Review TalkBack after deadline" />
            <permission name="Naaya - Skip Captcha" />
            <permission name="Naaya - Skip approval" />
            <permission name="Naaya - Translate pages" />
            <permission name="Naaya - Validate content" />
            <permission name="Naaya - View Naaya Survey Answers" />
            <permission name="Naaya - View Naaya Survey Reports" />
            <permission name="Naaya - Zip export" />
            <permission name="View"  />
        </role>

        <role name="Anonymous">
            <permission name="Access Transient Objects" />
            <permission name="Access contents information" />
            <permission name="Access session data" />
            <permission name="Naaya - Zip export" />
            <permission name="Naaya - Create user" />
            <permission name="Query Vocabulary" />
            <permission name="Search ZCatalog" />
            <permission name="Use Database Methods" />
            <permission name="Use mailhost services" />
            <permission name="View" />
            <permission name="WebDAV Lock items" />
            <permission name="WebDAV Unlock items" />
            <permission name="WebDAV access" />
        </role>

        <role name="Authenticated">
            <permission name="Add Naaya Forum Message" />
            <permission name="Naaya - Add comments for content" />
            <permission name="Naaya - Zip export" />
            <permission name="Naaya - Skip Captcha" />
            <permission name="Naaya - Add comments for content" />
        </role>

        <role name="Contributor">
            <permission name="Add Naaya Forum Message" />
            <permission name="Add/Edit/Delete Naaya Forum Topic" />
            <permission name="Naaya - Add Naaya Blob File objects" />
            <permission name="Naaya - Add Naaya Contact objects" />
            <permission name="Naaya - Add Naaya Document objects" />
            <permission name="Naaya - Add Naaya Event objects" />
            <permission name="Naaya - Add Naaya Folder objects" />
            <permission name="Naaya - Add Naaya Media File objects" />
            <permission name="Naaya - Add Naaya News objects" />
            <permission name="Naaya - Add Naaya Photo" />
            <permission name="Naaya - Add Naaya Pointer objects" />
            <permission name="Naaya - Add Naaya Story objects" />
            <permission name="Naaya - Add Naaya Survey Answer" />
            <permission name="Naaya - Add Naaya Survey Attachment" />
            <permission name="Naaya - Add Naaya URL objects" />
            <permission name="Naaya - Add Naaya Youtube objects" />
            <permission name="Naaya - Add comments for content" />
            <permission name="Naaya - Skip approval" />
            <permission name="View" />
        </role>

        <role name="Manager">
            <permission name="Access Transient Objects" />
            <permission name="Access contents information" />
            <permission name="Access session data" />
            <permission name="Add Naaya Forum" />
            <permission name="Add Naaya Forum Message" />
            <permission name="Add/Edit/Delete Naaya Forum Topic" />
            <permission name="Change permissions" />
            <permission name="Edit/Delete Forum Message" />
            <permission name="Manage users" />
            <permission name="Naaya - Access administrative area" />
            <permission name="Naaya - Add comments for content" />
            <permission name="Naaya - Add Naaya Blob File objects" />
            <permission name="Naaya - Add Naaya Contact objects" />
            <permission name="Naaya - Add Naaya Document objects" />
            <permission name="Naaya - Add Naaya Event objects" />
            <permission name="Naaya - Add Naaya Folder objects" />
            <permission name="Naaya - Add Naaya GeoPoint objects" />
            <permission name="Naaya - Add Naaya Media File objects" />
            <permission name="Naaya - Add Naaya Meeting objects" />
            <permission name="Naaya - Add Naaya Mega Survey" />
            <permission name="Naaya - Add Naaya News objects": />
            <permission name="Naaya - Add Naaya Photo" />
            <permission name="Naaya - Add Naaya Photo Folder" />
            <permission name="Naaya - Add Naaya Photo Gallery" />
            <permission name="Naaya - Add Naaya Pointer objects" />
            <permission name="Naaya - Add Naaya Story objects" />
            <permission name="Naaya - Add Naaya Survey Answer" />
            <permission name="Naaya - Add Naaya Survey Attachment" />
            <permission name="Naaya - Add Naaya Survey Report" />
            <permission name="Naaya - Add Naaya TalkBack Consultation objects" />
            <permission name="Naaya - Add Naaya URL objects" />
            <permission name="Naaya - Add Naaya Youtube objects" />
            <permission name="Naaya - Copy content" />
            <permission name="Naaya - Create user" />
            <permission name="Naaya - Delete content" />
            <permission name="Naaya - Edit Naaya Survey Answers" />
            <permission name="Naaya - Edit content" />
            <permission name="Naaya - Invite to TalkBack Consultation" />
            <permission name="Naaya - Manage TalkBack Consultation" />
            <permission name="Naaya - Manage comments for content" />
            <permission name="Naaya - Meeting - Administrate the meeting" />
            <permission name="Naaya - Meeting - Participate in the meeting" />
            <permission name="Naaya - Publish content" />
            <permission name="Naaya - Publish direct" />
            <permission name="Naaya - Request Webex" />
            <permission name="Naaya - Review TalkBack Consultation" />
            <permission name="Naaya - Review TalkBack after deadline" />
            <permission name="Naaya - Skip Captcha" />
            <permission name="Naaya - Skip approval" />
            <permission name="Naaya - Translate pages" />
            <permission name="Naaya - Validate content" />
            <permission name="Naaya - View Naaya Survey Answers" />
            <permission name="Naaya - View Naaya Survey Reports" />
            <permission name="Naaya - Zip export" />
            <permission name="View"  />
        </role>

        <role name="Owner">
            <permission name="Add/Edit/Delete Naaya Forum Topic" />
            <permission name="Add Naaya Forum Message" />
            <permission name="Edit/Delete Forum Message" />
            <permission name="Naaya - Add comments for content" />
            <permission name="Naaya - Copy content" />
            <permission name="Naaya - Delete content" />
            <permission name="Naaya - Edit content" />
            <permission name="Naaya - Skip Captcha" />
            <permission name="Naaya - Skip approval" />
            <permission name="Naaya - Zip export" />
            <permission name="View"  />
        </role>

        <role name="Reviewer">
            <permission name="Naaya - Add comments for content" />
            <permission name="Naaya - Review TalkBack Consultation" />
            <permission name="View" />
        </role>
    </security>
    <notification>
        <newsmetatype meta_type="Naaya News" action="1"/>
        <newsmetatype meta_type="Naaya Story" action="1"/>
        <newsmetatype meta_type="Naaya Event" action="1"/>
        <uploadmetatype meta_type="Naaya URL" action="1"/>
        <uploadmetatype meta_type="Naaya Document" action="1"/>
        <uploadmetatype meta_type="Naaya File" action="1"/>
        <foldermetatype meta_type="Naaya Folder" action="1"/>
    </notification>
    <others>
        <favicon />
        <robots />
        <images />
        <nyexp_schema url="http://svn.eionet.eu.int/repositories/Zope/trunk/Naaya/NaayaDocuments/schemas/naaya/naaya-nyexp-1.0.0.xsd"/>
    </others>
</skel>
